LICENSE
MANIFEST.in
README.rst
VERSION
nose_pudb.py
setup.py
nose_pudb.egg-info/PKG-INFO
nose_pudb.egg-info/SOURCES.txt
nose_pudb.egg-info/dependency_links.txt
nose_pudb.egg-info/entry_points.txt
nose_pudb.egg-info/requires.txt
nose_pudb.egg-info/top_level.txt