Metadata-Version: 1.1
Name: nose-pudb
Version: 1.0
Summary: A nose plugin for dropping into pudb on test errors or failures.
Home-page: https://github.com/AntoineD/nose-pudb
Author: Antoine Dechaume
Author-email: UNKNOWN
License: GNU Library or Lesser General Public License (LGPL)
Download-URL: https://pypi.python.org/pypi/nose-pudb
Keywords: test unittest nose plugin debugger pudb
Platform: POSIX
Classifier: Development Status :: 5 - Production/Stable
Classifier: Intended Audience :: Developers
Classifier: License :: OSI Approved :: GNU Library or Lesser General Public License (LGPL)
Classifier: Natural Language :: English
Classifier: Environment :: Plugins
Classifier: Programming Language :: Python
Classifier: Programming Language :: Python :: 2.6
Classifier: Programming Language :: Python :: 2.7
Classifier: Programming Language :: Python :: 3.3
Classifier: Programming Language :: Python :: 3.4
Classifier: Topic :: Software Development :: Testing
Classifier: Topic :: Software Development :: Debuggers
